{
  "scene_id": 304,
  "level_id": 2,
  "coordinate_system": {
    "x": "left",
    "y": "front",
    "z": "up"
  },
  "cameras": {
    "front_camera": {
      "position": [
        -1.0,
        9.0,
        4.0
      ],
      "lookat": [
        -1.0,
        1.0,
        1.4
      ],
      "focal_length": 20.0
    },
    "side_camera": {
      "position": [
        -9.0,
        1.0,
        4.0
      ],
      "lookat": [
        -1.0,
        1.0,
        1.4
      ],
      "focal_length": 20.0
    },
    "top_camera": {
      "position": [
        -1.0,
        1.0,
        9.6
      ],
      "lookat": [
        -1.0,
        1.0,
        1.4
      ],
      "focal_length": 18.0
    }
  },
  "images": {
    "front_camera": "304_front_camera.png",
    "side_camera": "304_side_camera.png",
    "top_camera": "304_top_camera.png"
  },
  "objects": [
    {
      "name": "obj_0",
      "tower_id": 0,
      "z_layer": 0,
      "shape": "cube",
      "size_name": "small",
      "color_name": "blue",
      "material_name": "rubber",
      "position": [
        -4.0,
        2.0,
        0.35
      ]
    },
    {
      "name": "obj_1",
      "tower_id": 1,
      "z_layer": 0,
      "shape": "cylinder",
      "size_name": "large",
      "color_name": "cyan",
      "material_name": "metal",
      "position": [
        -2.0,
        -2.0,
        0.7
      ]
    },
    {
      "name": "obj_2",
      "tower_id": 2,
      "z_layer": 0,
      "shape": "sphere",
      "size_name": "small",
      "color_name": "cyan",
      "material_name": "rubber",
      "position": [
        -4.0,
        -2.0,
        0.35
      ]
    },
    {
      "name": "obj_3",
      "tower_id": 3,
      "z_layer": 0,
      "shape": "cube",
      "size_name": "small",
      "color_name": "green",
      "material_name": "metal",
      "position": [
        0.0,
        -2.0,
        0.35
      ]
    }
  ],
  "visibility_stats": {
    "front_camera": {
      "obj_0": {
        "visible_pixels": 1125,
        "full_pixels": 1125,
        "visibility_ratio": 1.0,
        "is_visible": true,
        "bbox": [
          285,
          346,
          323,
          385
        ],
        "distance": 8.445
      },
      "obj_1": {
        "visible_pixels": 1243,
        "full_pixels": 1243,
        "visibility_ratio": 1.0,
        "is_visible": true,
        "bbox": [
          229,
          263,
          270,
          299
        ],
        "distance": 11.528
      },
      "obj_2": {
        "visible_pixels": 239,
        "full_pixels": 239,
        "visibility_ratio": 1.0,
        "is_visible": true,
        "bbox": [
          249,
          321,
          265,
          338
        ],
        "distance": 11.972
      },
      "obj_3": {
        "visible_pixels": 461,
        "full_pixels": 461,
        "visibility_ratio": 1.0,
        "is_visible": true,
        "bbox": [
          247,
          219,
          269,
          242
        ],
        "distance": 11.633
      }
    },
    "side_camera": {
      "obj_0": {
        "visible_pixels": 1914,
        "full_pixels": 1914,
        "visibility_ratio": 1.0,
        "is_visible": true,
        "bbox": [
          323,
          185,
          378,
          230
        ],
        "distance": 6.271
      },
      "obj_1": {
        "visible_pixels": 3492,
        "full_pixels": 3492,
        "visibility_ratio": 1.0,
        "is_visible": true,
        "bbox": [
          266,
          335,
          318,
          405
        ],
        "distance": 8.3
      },
      "obj_2": {
        "visible_pixels": 1051,
        "full_pixels": 1051,
        "visibility_ratio": 1.0,
        "is_visible": true,
        "bbox": [
          332,
          383,
          366,
          420
        ],
        "distance": 6.879
      },
      "obj_3": {
        "visible_pixels": 171,
        "full_pixels": 658,
        "visibility_ratio": 0.2599,
        "is_visible": true,
        "bbox": [
          262,
          330,
          286,
          354
        ],
        "distance": 10.165
      }
    },
    "top_camera": {
      "obj_0": {
        "visible_pixels": 534,
        "full_pixels": 534,
        "visibility_ratio": 1.0,
        "is_visible": true,
        "bbox": [
          270,
          324,
          297,
          354
        ],
        "distance": 9.776
      },
      "obj_1": {
        "visible_pixels": 1994,
        "full_pixels": 1994,
        "visibility_ratio": 1.0,
        "is_visible": true,
        "bbox": [
          141,
          265,
          193,
          304
        ],
        "distance": 9.445
      },
      "obj_2": {
        "visible_pixels": 323,
        "full_pixels": 323,
        "visibility_ratio": 1.0,
        "is_visible": true,
        "bbox": [
          163,
          329,
          182,
          348
        ],
        "distance": 10.177
      },
      "obj_3": {
        "visible_pixels": 535,
        "full_pixels": 535,
        "visibility_ratio": 1.0,
        "is_visible": true,
        "bbox": [
          156,
          214,
          188,
          241
        ],
        "distance": 9.776
      }
    }
  }
}