{
  "scene_id": 131,
  "level_id": 2,
  "coordinate_system": {
    "x": "left",
    "y": "front",
    "z": "up"
  },
  "cameras": {
    "front_camera": {
      "position": [
        -1.0,
        9.0,
        4.0
      ],
      "lookat": [
        -1.0,
        1.0,
        1.4
      ],
      "focal_length": 20.0
    },
    "side_camera": {
      "position": [
        -9.0,
        1.0,
        4.0
      ],
      "lookat": [
        -1.0,
        1.0,
        1.4
      ],
      "focal_length": 20.0
    },
    "top_camera": {
      "position": [
        -1.0,
        1.0,
        9.6
      ],
      "lookat": [
        -1.0,
        1.0,
        1.4
      ],
      "focal_length": 18.0
    }
  },
  "images": {
    "front_camera": "131_front_camera.png",
    "side_camera": "131_side_camera.png",
    "top_camera": "131_top_camera.png"
  },
  "objects": [
    {
      "name": "obj_0",
      "tower_id": 0,
      "z_layer": 0,
      "shape": "sphere",
      "size_name": "small",
      "color_name": "gray",
      "material_name": "rubber",
      "position": [
        0.0,
        4.0,
        0.35
      ]
    },
    {
      "name": "obj_1",
      "tower_id": 1,
      "z_layer": 0,
      "shape": "cube",
      "size_name": "large",
      "color_name": "green",
      "material_name": "metal",
      "position": [
        2.0,
        2.0,
        0.7
      ]
    },
    {
      "name": "obj_2",
      "tower_id": 2,
      "z_layer": 0,
      "shape": "cylinder",
      "size_name": "small",
      "color_name": "brown",
      "material_name": "rubber",
      "position": [
        2.0,
        0.0,
        0.35
      ]
    },
    {
      "name": "obj_3",
      "tower_id": 3,
      "z_layer": 0,
      "shape": "cylinder",
      "size_name": "small",
      "color_name": "cyan",
      "material_name": "rubber",
      "position": [
        -4.0,
        4.0,
        0.35
      ]
    }
  ],
  "visibility_stats": {
    "front_camera": {
      "obj_0": {
        "visible_pixels": 963,
        "full_pixels": 963,
        "visibility_ratio": 1.0,
        "is_visible": true,
        "bbox": [
          332,
          190,
          366,
          224
        ],
        "distance": 6.271
      },
      "obj_1": {
        "visible_pixels": 4678,
        "full_pixels": 4678,
        "visibility_ratio": 1.0,
        "is_visible": true,
        "bbox": [
          258,
          101,
          330,
          181
        ],
        "distance": 8.3
      },
      "obj_2": {
        "visible_pixels": 0,
        "full_pixels": 524,
        "visibility_ratio": 0.0,
        "is_visible": false,
        "bbox": [
          0,
          0,
          0,
          0
        ],
        "distance": 10.165
      },
      "obj_3": {
        "visible_pixels": 1630,
        "full_pixels": 1630,
        "visibility_ratio": 1.0,
        "is_visible": true,
        "bbox": [
          326,
          378,
          373,
          426
        ],
        "distance": 6.879
      }
    },
    "side_camera": {
      "obj_0": {
        "visible_pixels": 349,
        "full_pixels": 349,
        "visibility_ratio": 1.0,
        "is_visible": true,
        "bbox": [
          266,
          157,
          286,
          178
        ],
        "distance": 10.165
      },
      "obj_1": {
        "visible_pixels": 1749,
        "full_pixels": 1749,
        "visibility_ratio": 1.0,
        "is_visible": true,
        "bbox": [
          228,
          208,
          272,
          251
        ],
        "distance": 11.528
      },
      "obj_2": {
        "visible_pixels": 342,
        "full_pixels": 342,
        "visibility_ratio": 1.0,
        "is_visible": true,
        "bbox": [
          247,
          272,
          268,
          288
        ],
        "distance": 11.633
      },
      "obj_3": {
        "visible_pixels": 1589,
        "full_pixels": 1589,
        "visibility_ratio": 1.0,
        "is_visible": true,
        "bbox": [
          332,
          85,
          366,
          134
        ],
        "distance": 6.879
      }
    },
    "top_camera": {
      "obj_0": {
        "visible_pixels": 314,
        "full_pixels": 314,
        "visibility_ratio": 1.0,
        "is_visible": true,
        "bbox": [
          329,
          219,
          348,
          237
        ],
        "distance": 9.776
      },
      "obj_1": {
        "visible_pixels": 2360,
        "full_pixels": 2360,
        "visibility_ratio": 1.0,
        "is_visible": true,
        "bbox": [
          260,
          137,
          312,
          197
        ],
        "distance": 9.445
      },
      "obj_2": {
        "visible_pixels": 416,
        "full_pixels": 416,
        "visibility_ratio": 1.0,
        "is_visible": true,
        "bbox": [
          217,
          160,
          238,
          184
        ],
        "distance": 9.776
      },
      "obj_3": {
        "visible_pixels": 471,
        "full_pixels": 471,
        "visibility_ratio": 1.0,
        "is_visible": true,
        "bbox": [
          327,
          329,
          351,
          348
        ],
        "distance": 10.177
      }
    }
  }
}